[
  {
    "id": "SALE-0",
    "repName": "Ravi Patel",
    "dealSize": 622.42,
    "isWon": true,
    "commission": 1832.4,
    "dealProfit": 10755.42,
    "dealValue": 19917.44,
    "profitMargin": 0.54,
    "closeDate": "2025-07-23",
    "category": "Services"
  },
  {
    "id": "SALE-1",
    "repName": "James Wilson",
    "dealSize": 8685.05,
    "isWon": true,
    "commission": 1806.49,
    "dealProfit": 7642.84,
    "dealValue": 17370.1,
    "profitMargin": 0.44,
    "closeDate": "2025-07-29",
    "category": "Hardware"
  },
  {
    "id": "SALE-2",
    "repName": "James Wilson",
    "dealSize": 19203.48,
    "isWon": false,
    "commission": 0,
    "dealProfit": 0,
    "dealValue": 19203.48,
    "profitMargin": 0.19,
    "closeDate": "2025-10-08",
    "category": "Software"
  },
  {
    "id": "SALE-3",
    "repName": "Andreas Schmitt",
    "dealSize": 401.41,
    "isWon": true,
    "commission": 2742.43,
    "dealProfit": 18609.37,
    "dealValue": 24486.01,
    "profitMargin": 0.76,
    "closeDate": "2025-08-15",
    "category": "Services"
  },
  {
    "id": "SALE-4",
    "repName": "Sophie Dubois",
    "dealSize": 352.1,
    "isWon": false,
    "commission": 0,
    "dealProfit": 0,
    "dealValue": 30280.6,
    "profitMargin": 0.72,
    "closeDate": "2025-08-08",
    "category": "Support"
  },
  {
    "id": "SALE-5",
    "repName": "Jessica Lee",
    "dealSize": 8389.55,
    "isWon": true,
    "commission": 1443,
    "dealProfit": 5537.1,
    "dealValue": 16779.1,
    "profitMargin": 0.33,
    "closeDate": "2025-08-03",
    "category": "Software"
  },
  {
    "id": "SALE-6",
    "repName": "Thomas Müller",
    "dealSize": 7409.56,
    "isWon": true,
    "commission": 7483.66,
    "dealProfit": 14078.16,
    "dealValue": 74095.6,
    "profitMargin": 0.19,
    "closeDate": "2025-09-02",
    "category": "Training"
  },
  {
    "id": "SALE-7",
    "repName": "James Wilson",
    "dealSize": 8622.25,
    "isWon": true,
    "commission": 2690.14,
    "dealProfit": 7242.69,
    "dealValue": 25866.75,
    "profitMargin": 0.28,
    "closeDate": "2025-09-16",
    "category": "Hardware"
  },
  {
    "id": "SALE-8",
    "repName": "Sophie Dubois",
    "dealSize": 18457.12,
    "isWon": false,
    "commission": 0,
    "dealProfit": 0,
    "dealValue": 55371.36,
    "profitMargin": 0.17,
    "closeDate": "2025-09-07",
    "category": "Services"
  },
  {
    "id": "SALE-9",
    "repName": "Emily Davis",
    "dealSize": 16403.1,
    "isWon": false,
    "commission": 0,
    "dealProfit": 0,
    "dealValue": 49209.3,
    "profitMargin": 0.26,
    "closeDate": "2025-10-07",
    "category": "Training"
  },
  {
    "id": "SALE-10",
    "repName": "Liu Wei",
    "dealSize": 2410.08,
    "isWon": false,
    "commission": 0,
    "dealProfit": 0,
    "dealValue": 12050.4,
    "profitMargin": 0.59,
    "closeDate": "2025-09-02",
    "category": "Hardware"
  },
  {
    "id": "SALE-11",
    "repName": "Andreas Schmitt",
    "dealSize": 326,
    "isWon": false,
    "commission": 0,
    "dealProfit": 0,
    "dealValue": 57050,
    "profitMargin": 0.66,
    "closeDate": "2025-09-16",
    "category": "Support"
  },
  {
    "id": "SALE-12",
    "repName": "Ravi Patel",
    "dealSize": 100.02,
    "isWon": false,
    "commission": 0,
    "dealProfit": 0,
    "dealValue": 17503.5,
    "profitMargin": 0.66,
    "closeDate": "2025-07-28",
    "category": "Software"
  },
  {
    "id": "SALE-13",
    "repName": "David Thompson",
    "dealSize": 31539.63,
    "isWon": true,
    "commission": 5614.05,
    "dealProfit": 19554.57,
    "dealValue": 63079.26,
    "profitMargin": 0.31,
    "closeDate": "2025-09-29",
    "category": "Services"
  },
  {
    "id": "SALE-14",
    "repName": "Emily Davis",
    "dealSize": 9773.2,
    "isWon": false,
    "commission": 0,
    "dealProfit": 0,
    "dealValue": 19546.4,
    "profitMargin": 0.41,
    "closeDate": "2025-08-13",
    "category": "Training"
  },
  {
    "id": "SALE-15",
    "repName": "Thomas Müller",
    "dealSize": 397.1,
    "isWon": true,
    "commission": 3795.88,
    "dealProfit": 24155.59,
    "dealValue": 31370.9,
    "profitMargin": 0.77,
    "closeDate": "2025-07-23",
    "category": "Consulting"
  },
  {
    "id": "SALE-16",
    "repName": "James Wilson",
    "dealSize": 126.8,
    "isWon": true,
    "commission": 487.42,
    "dealProfit": 2712.25,
    "dealValue": 3930.8,
    "profitMargin": 0.69,
    "closeDate": "2025-07-21",
    "category": "Training"
  },
  {
    "id": "SALE-17",
    "repName": "Pierre Laurent",
    "dealSize": 310.41,
    "isWon": true,
    "commission": 6087.14,
    "dealProfit": 41346.61,
    "dealValue": 57425.85,
    "profitMargin": 0.72,
    "closeDate": "2025-08-07",
    "category": "Consulting"
  },
  {
    "id": "SALE-18",
    "repName": "Emily Davis",
    "dealSize": 340.29,
    "isWon": false,
    "commission": 0,
    "dealProfit": 0,
    "dealValue": 3402.9,
    "profitMargin": 0.74,
    "closeDate": "2025-10-02",
    "category": "Services"
  },
  {
    "id": "SALE-19",
    "repName": "Emma Fischer",
    "dealSize": 319.3,
    "isWon": true,
    "commission": 3025.69,
    "dealProfit": 19975.41,
    "dealValue": 29375.6,
    "profitMargin": 0.68,
    "closeDate": "2025-09-24",
    "category": "Software"
  },
  {
    "id": "SALE-20",
    "repName": "Jessica Lee",
    "dealSize": 15258.82,
    "isWon": true,
    "commission": 2624.52,
    "dealProfit": 7324.23,
    "dealValue": 30517.64,
    "profitMargin": 0.24,
    "closeDate": "2025-08-24",
    "category": "Training"
  },
  {
    "id": "SALE-21",
    "repName": "Carlos Rodriguez",
    "dealSize": 357.74,
    "isWon": true,
    "commission": 5718.47,
    "dealProfit": 38288.91,
    "dealValue": 49725.86,
    "profitMargin": 0.77,
    "closeDate": "2025-08-06",
    "category": "Software"
  },
  {
    "id": "SALE-22",
    "repName": "Emily Davis",
    "dealSize": 412.25,
    "isWon": true,
    "commission": 6956.31,
    "dealProfit": 45982.37,
    "dealValue": 58951.75,
    "profitMargin": 0.78,
    "closeDate": "2025-09-24",
    "category": "Hardware"
  },
  {
    "id": "SALE-23",
    "repName": "Andreas Schmitt",
    "dealSize": 102.83,
    "isWon": false,
    "commission": 0,
    "dealProfit": 0,
    "dealValue": 19229.21,
    "profitMargin": 0.79,
    "closeDate": "2025-08-28",
    "category": "Consulting"
  },
  {
    "id": "SALE-24",
    "repName": "Valentina Diaz",
    "dealSize": 115,
    "isWon": true,
    "commission": 1255.57,
    "dealProfit": 8533,
    "dealValue": 12190,
    "profitMargin": 0.7,
    "closeDate": "2025-09-14",
    "category": "Support"
  },
  {
    "id": "SALE-25",
    "repName": "Liu Wei",
    "dealSize": 3285.66,
    "isWon": true,
    "commission": 2575.96,
    "dealProfit": 11828.38,
    "dealValue": 26285.28,
    "profitMargin": 0.45,
    "closeDate": "2025-08-24",
    "category": "Services"
  },
  {
    "id": "SALE-26",
    "repName": "Thomas Müller",
    "dealSize": 334.98,
    "isWon": false,
    "commission": 0,
    "dealProfit": 0,
    "dealValue": 63311.22,
    "profitMargin": 0.63,
    "closeDate": "2025-08-25",
    "category": "Support"
  },
  {
    "id": "SALE-27",
    "repName": "Sophie Dubois",
    "dealSize": 9593.78,
    "isWon": true,
    "commission": 3645.64,
    "dealProfit": 8826.28,
    "dealValue": 38375.12,
    "profitMargin": 0.23,
    "closeDate": "2025-08-26",
    "category": "Services"
  },
  {
    "id": "SALE-28",
    "repName": "Akira Tanaka",
    "dealSize": 18673.21,
    "isWon": true,
    "commission": 1773.95,
    "dealProfit": 4668.3,
    "dealValue": 18673.21,
    "profitMargin": 0.25,
    "closeDate": "2025-10-07",
    "category": "Software"
  },
  {
    "id": "SALE-29",
    "repName": "James Wilson",
    "dealSize": 30222.87,
    "isWon": true,
    "commission": 6286.36,
    "dealProfit": 27805.04,
    "dealValue": 60445.74,
    "profitMargin": 0.46,
    "closeDate": "2025-08-30",
    "category": "Training"
  },
  {
    "id": "SALE-30",
    "repName": "Emily Davis",
    "dealSize": 386.15,
    "isWon": true,
    "commission": 3462.99,
    "dealProfit": 20249.71,
    "dealValue": 29347.4,
    "profitMargin": 0.69,
    "closeDate": "2025-08-09",
    "category": "Hardware"
  },
  {
    "id": "SALE-31",
    "repName": "Andreas Schmitt",
    "dealSize": 126.24,
    "isWon": true,
    "commission": 1583.55,
    "dealProfit": 9331.66,
    "dealValue": 14138.88,
    "profitMargin": 0.66,
    "closeDate": "2025-07-16",
    "category": "Software"
  },
  {
    "id": "SALE-32",
    "repName": "Akira Tanaka",
    "dealSize": 6355.74,
    "isWon": false,
    "commission": 0,
    "dealProfit": 0,
    "dealValue": 120759.06,
    "profitMargin": 0.41,
    "closeDate": "2025-09-19",
    "category": "Training"
  },
  {
    "id": "SALE-33",
    "repName": "Liu Wei",
    "dealSize": 138.41,
    "isWon": true,
    "commission": 1845.56,
    "dealProfit": 11417.44,
    "dealValue": 15640.33,
    "profitMargin": 0.73,
    "closeDate": "2025-10-06",
    "category": "Hardware"
  },
  {
    "id": "SALE-34",
    "repName": "Emily Davis",
    "dealSize": 9716.58,
    "isWon": true,
    "commission": 1904.45,
    "dealProfit": 7384.6,
    "dealValue": 19433.16,
    "profitMargin": 0.38,
    "closeDate": "2025-08-22",
    "category": "Software"
  },
  {
    "id": "SALE-35",
    "repName": "Carlos Rodriguez",
    "dealSize": 614.78,
    "isWon": false,
    "commission": 0,
    "dealProfit": 0,
    "dealValue": 56559.76,
    "profitMargin": 0.59,
    "closeDate": "2025-08-08",
    "category": "Consulting"
  },
  {
    "id": "SALE-36",
    "repName": "James Wilson",
    "dealSize": 6766.8,
    "isWon": false,
    "commission": 0,
    "dealProfit": 0,
    "dealValue": 6766.8,
    "profitMargin": 0.38,
    "closeDate": "2025-10-12",
    "category": "Software"
  },
  {
    "id": "SALE-37",
    "repName": "Olivia Bennett",
    "dealSize": 30620.66,
    "isWon": true,
    "commission": 2725.24,
    "dealProfit": 13473.09,
    "dealValue": 30620.66,
    "profitMargin": 0.44,
    "closeDate": "2025-09-23",
    "category": "Support"
  },
  {
    "id": "SALE-38",
    "repName": "Ravi Patel",
    "dealSize": 8547.64,
    "isWon": true,
    "commission": 5504.68,
    "dealProfit": 17950.04,
    "dealValue": 59833.48,
    "profitMargin": 0.3,
    "closeDate": "2025-08-10",
    "category": "Consulting"
  },
  {
    "id": "SALE-39",
    "repName": "Pierre Laurent",
    "dealSize": 633.6,
    "isWon": true,
    "commission": 9426.7,
    "dealProfit": 63575.42,
    "dealValue": 109612.8,
    "profitMargin": 0.58,
    "closeDate": "2025-08-15",
    "category": "Training"
  },
  {
    "id": "SALE-40",
    "repName": "Thomas Müller",
    "dealSize": 33344.23,
    "isWon": true,
    "commission": 3367.77,
    "dealProfit": 12337.37,
    "dealValue": 33344.23,
    "profitMargin": 0.37,
    "closeDate": "2025-10-04",
    "category": "Training"
  },
  {
    "id": "SALE-41",
    "repName": "Thomas Müller",
    "dealSize": 367.47,
    "isWon": false,
    "commission": 0,
    "dealProfit": 0,
    "dealValue": 17638.56,
    "profitMargin": 0.8,
    "closeDate": "2025-08-02",
    "category": "Training"
  },
  {
    "id": "SALE-42",
    "repName": "Sophie Dubois",
    "dealSize": 99.4,
    "isWon": true,
    "commission": 1257.41,
    "dealProfit": 7325.78,
    "dealValue": 10934,
    "profitMargin": 0.67,
    "closeDate": "2025-09-03",
    "category": "Software"
  },
  {
    "id": "SALE-43",
    "repName": "Emily Davis",
    "dealSize": 8783.22,
    "isWon": true,
    "commission": 1721.51,
    "dealProfit": 7553.57,
    "dealValue": 17566.44,
    "profitMargin": 0.43,
    "closeDate": "2025-10-12",
    "category": "Support"
  },
  {
    "id": "SALE-44",
    "repName": "Emily Davis",
    "dealSize": 668.96,
    "isWon": true,
    "commission": 1376.72,
    "dealProfit": 6883.6,
    "dealValue": 14048.16,
    "profitMargin": 0.49,
    "closeDate": "2025-09-23",
    "category": "Services"
  },
  {
    "id": "SALE-45",
    "repName": "Isabella Fernandez",
    "dealSize": 584.93,
    "isWon": true,
    "commission": 6299.11,
    "dealProfit": 33972.73,
    "dealValue": 70776.53,
    "profitMargin": 0.48,
    "closeDate": "2025-08-15",
    "category": "Services"
  },
  {
    "id": "SALE-46",
    "repName": "Mei Chen",
    "dealSize": 2934.33,
    "isWon": false,
    "commission": 0,
    "dealProfit": 0,
    "dealValue": 5868.66,
    "profitMargin": 0.38,
    "closeDate": "2025-07-16",
    "category": "Hardware"
  },
  {
    "id": "SALE-47",
    "repName": "Liu Wei",
    "dealSize": 10661.36,
    "isWon": false,
    "commission": 0,
    "dealProfit": 0,
    "dealValue": 31984.08,
    "profitMargin": 0.44,
    "closeDate": "2025-08-20",
    "category": "Consulting"
  },
  {
    "id": "SALE-48",
    "repName": "Valentina Diaz",
    "dealSize": 114.51,
    "isWon": false,
    "commission": 0,
    "dealProfit": 0,
    "dealValue": 3664.32,
    "profitMargin": 0.62,
    "closeDate": "2025-08-14",
    "category": "Services"
  },
  {
    "id": "SALE-49",
    "repName": "James Wilson",
    "dealSize": 6216.7,
    "isWon": true,
    "commission": 3879.22,
    "dealProfit": 16785.09,
    "dealValue": 37300.2,
    "profitMargin": 0.45,
    "closeDate": "2025-09-12",
    "category": "Consulting"
  },
  {
    "id": "SALE-50",
    "repName": "James Wilson",
    "dealSize": 26358.78,
    "isWon": true,
    "commission": 8223.94,
    "dealProfit": 30839.77,
    "dealValue": 79076.34,
    "profitMargin": 0.39,
    "closeDate": "2025-10-08",
    "category": "Support"
  },
  {
    "id": "SALE-51",
    "repName": "Thomas Müller",
    "dealSize": 133.93,
    "isWon": true,
    "commission": 1523.32,
    "dealProfit": 7805.44,
    "dealValue": 12589.42,
    "profitMargin": 0.62,
    "closeDate": "2025-09-01",
    "category": "Hardware"
  },
  {
    "id": "SALE-52",
    "repName": "Sarah Martinez",
    "dealSize": 500.8,
    "isWon": true,
    "commission": 1796.87,
    "dealProfit": 10742.16,
    "dealValue": 19531.2,
    "profitMargin": 0.55,
    "closeDate": "2025-08-11",
    "category": "Consulting"
  },
  {
    "id": "SALE-53",
    "repName": "James Wilson",
    "dealSize": 8596.77,
    "isWon": true,
    "commission": 8940.64,
    "dealProfit": 18912.89,
    "dealValue": 85967.7,
    "profitMargin": 0.22,
    "closeDate": "2025-08-19",
    "category": "Consulting"
  },
  {
    "id": "SALE-54",
    "repName": "Emily Davis",
    "dealSize": 2472.59,
    "isWon": false,
    "commission": 0,
    "dealProfit": 0,
    "dealValue": 24725.9,
    "profitMargin": 0.51,
    "closeDate": "2025-10-04",
    "category": "Hardware"
  },
  {
    "id": "SALE-55",
    "repName": "Liu Wei",
    "dealSize": 19609.39,
    "isWon": true,
    "commission": 1921.72,
    "dealProfit": 4117.97,
    "dealValue": 19609.39,
    "profitMargin": 0.21,
    "closeDate": "2025-07-23",
    "category": "Hardware"
  },
  {
    "id": "SALE-56",
    "repName": "Michael Johnson",
    "dealSize": 2273.62,
    "isWon": true,
    "commission": 3887.89,
    "dealProfit": 24555.1,
    "dealValue": 40925.16,
    "profitMargin": 0.6,
    "closeDate": "2025-08-28",
    "category": "Training"
  },
  {
    "id": "SALE-57",
    "repName": "Michael Johnson",
    "dealSize": 7687.59,
    "isWon": true,
    "commission": 2921.28,
    "dealProfit": 10147.62,
    "dealValue": 30750.36,
    "profitMargin": 0.33,
    "closeDate": "2025-09-04",
    "category": "Software"
  },
  {
    "id": "SALE-58",
    "repName": "Liu Wei",
    "dealSize": 401.17,
    "isWon": true,
    "commission": 2366.9,
    "dealProfit": 12837.44,
    "dealValue": 20058.5,
    "profitMargin": 0.64,
    "closeDate": "2025-10-01",
    "category": "Hardware"
  },
  {
    "id": "SALE-59",
    "repName": "Emily Davis",
    "dealSize": 1660.2,
    "isWon": true,
    "commission": 3526.26,
    "dealProfit": 22412.7,
    "dealValue": 29883.6,
    "profitMargin": 0.75,
    "closeDate": "2025-09-17",
    "category": "Consulting"
  },
  {
    "id": "SALE-60",
    "repName": "Sophie Dubois",
    "dealSize": 686.95,
    "isWon": true,
    "commission": 8027.01,
    "dealProfit": 39712.58,
    "dealValue": 84494.85,
    "profitMargin": 0.47,
    "closeDate": "2025-07-24",
    "category": "Support"
  },
  {
    "id": "SALE-61",
    "repName": "Sarah Martinez",
    "dealSize": 350.64,
    "isWon": false,
    "commission": 0,
    "dealProfit": 0,
    "dealValue": 29103.12,
    "profitMargin": 0.79,
    "closeDate": "2025-08-10",
    "category": "Consulting"
  },
  {
    "id": "SALE-62",
    "repName": "Thomas Müller",
    "dealSize": 8305.88,
    "isWon": true,
    "commission": 15938.98,
    "dealProfit": 53655.98,
    "dealValue": 157811.72,
    "profitMargin": 0.34,
    "closeDate": "2025-09-02",
    "category": "Consulting"
  },
  {
    "id": "SALE-63",
    "repName": "Sarah Martinez",
    "dealSize": 10673.86,
    "isWon": true,
    "commission": 982,
    "dealProfit": 4909.98,
    "dealValue": 10673.86,
    "profitMargin": 0.46,
    "closeDate": "2025-08-01",
    "category": "Software"
  },
  {
    "id": "SALE-64",
    "repName": "Thomas Müller",
    "dealSize": 5813.08,
    "isWon": true,
    "commission": 2935.61,
    "dealProfit": 11626.16,
    "dealValue": 29065.4,
    "profitMargin": 0.4,
    "closeDate": "2025-10-12",
    "category": "Consulting"
  },
  {
    "id": "SALE-65",
    "repName": "Ravi Patel",
    "dealSize": 3467.31,
    "isWon": false,
    "commission": 0,
    "dealProfit": 0,
    "dealValue": 17336.55,
    "profitMargin": 0.36,
    "closeDate": "2025-07-23",
    "category": "Support"
  },
  {
    "id": "SALE-66",
    "repName": "Andreas Schmitt",
    "dealSize": 108.23,
    "isWon": true,
    "commission": 957.62,
    "dealProfit": 5386.61,
    "dealValue": 8550.17,
    "profitMargin": 0.63,
    "closeDate": "2025-09-23",
    "category": "Services"
  },
  {
    "id": "SALE-67",
    "repName": "Emily Davis",
    "dealSize": 582.03,
    "isWon": true,
    "commission": 399.27,
    "dealProfit": 2363.04,
    "dealValue": 4074.21,
    "profitMargin": 0.58,
    "closeDate": "2025-09-30",
    "category": "Training"
  },
  {
    "id": "SALE-68",
    "repName": "Pierre Laurent",
    "dealSize": 358.87,
    "isWon": false,
    "commission": 0,
    "dealProfit": 0,
    "dealValue": 49882.93,
    "profitMargin": 0.72,
    "closeDate": "2025-09-17",
    "category": "Training"
  },
  {
    "id": "SALE-69",
    "repName": "David Thompson",
    "dealSize": 9198.38,
    "isWon": false,
    "commission": 0,
    "dealProfit": 0,
    "dealValue": 27595.14,
    "profitMargin": 0.46,
    "closeDate": "2025-10-10",
    "category": "Services"
  },
  {
    "id": "SALE-70",
    "repName": "Thomas Müller",
    "dealSize": 640.53,
    "isWon": false,
    "commission": 0,
    "dealProfit": 0,
    "dealValue": 16653.78,
    "profitMargin": 0.54,
    "closeDate": "2025-09-14",
    "category": "Services"
  },
  {
    "id": "SALE-71",
    "repName": "Liu Wei",
    "dealSize": 2309.38,
    "isWon": false,
    "commission": 0,
    "dealProfit": 0,
    "dealValue": 9237.52,
    "profitMargin": 0.64,
    "closeDate": "2025-09-11",
    "category": "Hardware"
  },
  {
    "id": "SALE-72",
    "repName": "Mei Chen",
    "dealSize": 630.11,
    "isWon": true,
    "commission": 9428.97,
    "dealProfit": 59205.14,
    "dealValue": 109639.14,
    "profitMargin": 0.54,
    "closeDate": "2025-10-01",
    "category": "Training"
  },
  {
    "id": "SALE-73",
    "repName": "Liu Wei",
    "dealSize": 111.8,
    "isWon": true,
    "commission": 1213.7,
    "dealProfit": 6582.78,
    "dealValue": 10285.6,
    "profitMargin": 0.64,
    "closeDate": "2025-10-07",
    "category": "Support"
  },
  {
    "id": "SALE-74",
    "repName": "Liu Wei",
    "dealSize": 128.5,
    "isWon": true,
    "commission": 894.62,
    "dealProfit": 5534.5,
    "dealValue": 7581.5,
    "profitMargin": 0.73,
    "closeDate": "2025-09-15",
    "category": "Support"
  },
  {
    "id": "SALE-75",
    "repName": "Isabella Fernandez",
    "dealSize": 683.78,
    "isWon": false,
    "commission": 0,
    "dealProfit": 0,
    "dealValue": 100515.66,
    "profitMargin": 0.47,
    "closeDate": "2025-09-29",
    "category": "Consulting"
  },
  {
    "id": "SALE-76",
    "repName": "Emily Davis",
    "dealSize": 2026.67,
    "isWon": true,
    "commission": 1390.3,
    "dealProfit": 7802.68,
    "dealValue": 14186.69,
    "profitMargin": 0.55,
    "closeDate": "2025-09-07",
    "category": "Training"
  },
  {
    "id": "SALE-77",
    "repName": "Michael Johnson",
    "dealSize": 133.76,
    "isWon": true,
    "commission": 2876.51,
    "dealProfit": 17509.18,
    "dealValue": 25013.12,
    "profitMargin": 0.7,
    "closeDate": "2025-08-18",
    "category": "Services"
  },
  {
    "id": "SALE-78",
    "repName": "Jessica Lee",
    "dealSize": 10272.76,
    "isWon": true,
    "commission": 2650.37,
    "dealProfit": 14176.41,
    "dealValue": 30818.28,
    "profitMargin": 0.46,
    "closeDate": "2025-09-15",
    "category": "Hardware"
  },
  {
    "id": "SALE-79",
    "repName": "Emma Fischer",
    "dealSize": 315.71,
    "isWon": false,
    "commission": 0,
    "dealProfit": 0,
    "dealValue": 6314.2,
    "profitMargin": 0.66,
    "closeDate": "2025-08-09",
    "category": "Consulting"
  },
  {
    "id": "SALE-80",
    "repName": "Emily Davis",
    "dealSize": 1587.44,
    "isWon": true,
    "commission": 3559.04,
    "dealProfit": 18096.82,
    "dealValue": 30161.36,
    "profitMargin": 0.6,
    "closeDate": "2025-07-16",
    "category": "Support"
  },
  {
    "id": "SALE-81",
    "repName": "Mateo Lopez",
    "dealSize": 6885.58,
    "isWon": true,
    "commission": 9474.56,
    "dealProfit": 50677.87,
    "dealValue": 110169.28,
    "profitMargin": 0.46,
    "closeDate": "2025-09-22",
    "category": "Training"
  },
  {
    "id": "SALE-82",
    "repName": "Isabella Fernandez",
    "dealSize": 364.43,
    "isWon": false,
    "commission": 0,
    "dealProfit": 0,
    "dealValue": 55028.93,
    "profitMargin": 0.63,
    "closeDate": "2025-08-28",
    "category": "Consulting"
  },
  {
    "id": "SALE-83",
    "repName": "James Wilson",
    "dealSize": 1550.26,
    "isWon": true,
    "commission": 768.93,
    "dealProfit": 4030.68,
    "dealValue": 6201.04,
    "profitMargin": 0.65,
    "closeDate": "2025-08-01",
    "category": "Hardware"
  },
  {
    "id": "SALE-84",
    "repName": "Ravi Patel",
    "dealSize": 2536.5,
    "isWon": false,
    "commission": 0,
    "dealProfit": 0,
    "dealValue": 45657,
    "profitMargin": 0.45,
    "closeDate": "2025-07-27",
    "category": "Training"
  },
  {
    "id": "SALE-85",
    "repName": "Emily Davis",
    "dealSize": 360.59,
    "isWon": true,
    "commission": 3701.82,
    "dealProfit": 24783.35,
    "dealValue": 31371.33,
    "profitMargin": 0.79,
    "closeDate": "2025-08-09",
    "category": "Support"
  },
  {
    "id": "SALE-86",
    "repName": "Sarah Martinez",
    "dealSize": 3034.86,
    "isWon": true,
    "commission": 279.21,
    "dealProfit": 1365.69,
    "dealValue": 3034.86,
    "profitMargin": 0.45,
    "closeDate": "2025-08-11",
    "category": "Software"
  },
  {
    "id": "SALE-87",
    "repName": "Emily Davis",
    "dealSize": 112.41,
    "isWon": false,
    "commission": 0,
    "dealProfit": 0,
    "dealValue": 14613.3,
    "profitMargin": 0.63,
    "closeDate": "2025-08-25",
    "category": "Support"
  },
  {
    "id": "SALE-88",
    "repName": "Jessica Lee",
    "dealSize": 5313.9,
    "isWon": true,
    "commission": 5940.94,
    "dealProfit": 23487.44,
    "dealValue": 69080.7,
    "profitMargin": 0.34,
    "closeDate": "2025-09-07",
    "category": "Support"
  },
  {
    "id": "SALE-89",
    "repName": "Isabella Fernandez",
    "dealSize": 134.84,
    "isWon": true,
    "commission": 308.65,
    "dealProfit": 2123.73,
    "dealValue": 2831.64,
    "profitMargin": 0.75,
    "closeDate": "2025-09-03",
    "category": "Consulting"
  },
  {
    "id": "SALE-90",
    "repName": "Valentina Diaz",
    "dealSize": 3523.37,
    "isWon": false,
    "commission": 0,
    "dealProfit": 0,
    "dealValue": 49327.18,
    "profitMargin": 0.49,
    "closeDate": "2025-07-25",
    "category": "Consulting"
  },
  {
    "id": "SALE-91",
    "repName": "Mateo Lopez",
    "dealSize": 398.92,
    "isWon": true,
    "commission": 2917.7,
    "dealProfit": 20368.86,
    "dealValue": 27525.48,
    "profitMargin": 0.74,
    "closeDate": "2025-09-23",
    "category": "Consulting"
  },
  {
    "id": "SALE-92",
    "repName": "James Wilson",
    "dealSize": 107.21,
    "isWon": false,
    "commission": 0,
    "dealProfit": 0,
    "dealValue": 15009.4,
    "profitMargin": 0.73,
    "closeDate": "2025-08-30",
    "category": "Software"
  },
  {
    "id": "SALE-93",
    "repName": "Thomas Müller",
    "dealSize": 402.16,
    "isWon": true,
    "commission": 9099.67,
    "dealProfit": 51890.7,
    "dealValue": 75203.92,
    "profitMargin": 0.69,
    "closeDate": "2025-08-27",
    "category": "Training"
  },
  {
    "id": "SALE-94",
    "repName": "Robert Garcia",
    "dealSize": 309.95,
    "isWon": false,
    "commission": 0,
    "dealProfit": 0,
    "dealValue": 44632.8,
    "profitMargin": 0.66,
    "closeDate": "2025-09-14",
    "category": "Services"
  },
  {
    "id": "SALE-95",
    "repName": "James Wilson",
    "dealSize": 623.8,
    "isWon": true,
    "commission": 2789.63,
    "dealProfit": 14484.64,
    "dealValue": 26823.4,
    "profitMargin": 0.54,
    "closeDate": "2025-09-07",
    "category": "Services"
  },
  {
    "id": "SALE-96",
    "repName": "Liu Wei",
    "dealSize": 379.37,
    "isWon": true,
    "commission": 5103.29,
    "dealProfit": 26813.87,
    "dealValue": 43248.18,
    "profitMargin": 0.62,
    "closeDate": "2025-07-19",
    "category": "Consulting"
  },
  {
    "id": "SALE-97",
    "repName": "Jessica Lee",
    "dealSize": 31185.78,
    "isWon": true,
    "commission": 2681.98,
    "dealProfit": 14657.32,
    "dealValue": 31185.78,
    "profitMargin": 0.47,
    "closeDate": "2025-09-03",
    "category": "Services"
  },
  {
    "id": "SALE-98",
    "repName": "Pierre Laurent",
    "dealSize": 5863.21,
    "isWon": false,
    "commission": 0,
    "dealProfit": 0,
    "dealValue": 111400.99,
    "profitMargin": 0.43,
    "closeDate": "2025-09-22",
    "category": "Consulting"
  },
  {
    "id": "SALE-99",
    "repName": "Michael Johnson",
    "dealSize": 303.3,
    "isWon": true,
    "commission": 4185.54,
    "dealProfit": 22201.56,
    "dealValue": 36396,
    "profitMargin": 0.61,
    "closeDate": "2025-10-12",
    "category": "Support"
  },
  {
    "id": "SALE-100",
    "repName": "Ravi Patel",
    "dealSize": 304.15,
    "isWon": true,
    "commission": 4019.65,
    "dealProfit": 24405,
    "dealValue": 35889.7,
    "profitMargin": 0.68,
    "closeDate": "2025-08-03",
    "category": "Consulting"
  },
  {
    "id": "SALE-101",
    "repName": "Sophie Dubois",
    "dealSize": 635.02,
    "isWon": true,
    "commission": 10134.92,
    "dealProfit": 61876.35,
    "dealValue": 106683.36,
    "profitMargin": 0.58,
    "closeDate": "2025-10-02",
    "category": "Services"
  },
  {
    "id": "SALE-102",
    "repName": "David Thompson",
    "dealSize": 402.07,
    "isWon": true,
    "commission": 175.3,
    "dealProfit": 1109.71,
    "dealValue": 1608.28,
    "profitMargin": 0.69,
    "closeDate": "2025-09-02",
    "category": "Software"
  },
  {
    "id": "SALE-103",
    "repName": "Isabella Fernandez",
    "dealSize": 317.77,
    "isWon": true,
    "commission": 6373.2,
    "dealProfit": 38005.29,
    "dealValue": 58469.68,
    "profitMargin": 0.65,
    "closeDate": "2025-08-07",
    "category": "Hardware"
  },
  {
    "id": "SALE-104",
    "repName": "Thomas Müller",
    "dealSize": 126.96,
    "isWon": true,
    "commission": 1382.59,
    "dealProfit": 8455.54,
    "dealValue": 11426.4,
    "profitMargin": 0.74,
    "closeDate": "2025-07-17",
    "category": "Services"
  },
  {
    "id": "SALE-105",
    "repName": "David Thompson",
    "dealSize": 121.5,
    "isWon": true,
    "commission": 1893.82,
    "dealProfit": 11293.43,
    "dealValue": 17374.5,
    "profitMargin": 0.65,
    "closeDate": "2025-09-19",
    "category": "Hardware"
  },
  {
    "id": "SALE-106",
    "repName": "Sarah Martinez",
    "dealSize": 7773.01,
    "isWon": true,
    "commission": 10011.64,
    "dealProfit": 38087.75,
    "dealValue": 108822.14,
    "profitMargin": 0.35,
    "closeDate": "2025-08-23",
    "category": "Support"
  },
  {
    "id": "SALE-107",
    "repName": "James Wilson",
    "dealSize": 17836.6,
    "isWon": false,
    "commission": 0,
    "dealProfit": 0,
    "dealValue": 35673.2,
    "profitMargin": 0.28,
    "closeDate": "2025-08-28",
    "category": "Support"
  },
  {
    "id": "SALE-108",
    "repName": "Ravi Patel",
    "dealSize": 7047.22,
    "isWon": false,
    "commission": 0,
    "dealProfit": 0,
    "dealValue": 7047.22,
    "profitMargin": 0.34,
    "closeDate": "2025-08-22",
    "category": "Training"
  },
  {
    "id": "SALE-109",
    "repName": "Mateo Lopez",
    "dealSize": 8709.99,
    "isWon": false,
    "commission": 0,
    "dealProfit": 0,
    "dealValue": 121939.86,
    "profitMargin": 0.26,
    "closeDate": "2025-09-23",
    "category": "Support"
  },
  {
    "id": "SALE-110",
    "repName": "James Wilson",
    "dealSize": 9913.31,
    "isWon": false,
    "commission": 0,
    "dealProfit": 0,
    "dealValue": 99133.1,
    "profitMargin": 0.32,
    "closeDate": "2025-09-17",
    "category": "Training"
  },
  {
    "id": "SALE-111",
    "repName": "Isabella Fernandez",
    "dealSize": 131.2,
    "isWon": true,
    "commission": 600.63,
    "dealProfit": 3636.86,
    "dealValue": 5510.4,
    "profitMargin": 0.66,
    "closeDate": "2025-08-27",
    "category": "Support"
  },
  {
    "id": "SALE-112",
    "repName": "Liu Wei",
    "dealSize": 575.16,
    "isWon": true,
    "commission": 10314.92,
    "dealProfit": 65257.65,
    "dealValue": 105254.28,
    "profitMargin": 0.62,
    "closeDate": "2025-09-17",
    "category": "Training"
  },
  {
    "id": "SALE-113",
    "repName": "Mateo Lopez",
    "dealSize": 2884.02,
    "isWon": false,
    "commission": 0,
    "dealProfit": 0,
    "dealValue": 14420.1,
    "profitMargin": 0.38,
    "closeDate": "2025-09-23",
    "category": "Services"
  },
  {
    "id": "SALE-114",
    "repName": "Sophie Dubois",
    "dealSize": 1525.5,
    "isWon": true,
    "commission": 701.73,
    "dealProfit": 3783.24,
    "dealValue": 6102,
    "profitMargin": 0.62,
    "closeDate": "2025-09-18",
    "category": "Hardware"
  },
  {
    "id": "SALE-115",
    "repName": "Isabella Fernandez",
    "dealSize": 400.58,
    "isWon": false,
    "commission": 0,
    "dealProfit": 0,
    "dealValue": 30844.66,
    "profitMargin": 0.69,
    "closeDate": "2025-07-29",
    "category": "Hardware"
  },
  {
    "id": "SALE-116",
    "repName": "Andreas Schmitt",
    "dealSize": 104.63,
    "isWon": false,
    "commission": 0,
    "dealProfit": 0,
    "dealValue": 16008.39,
    "profitMargin": 0.71,
    "closeDate": "2025-08-28",
    "category": "Consulting"
  },
  {
    "id": "SALE-117",
    "repName": "Sarah Martinez",
    "dealSize": 124.04,
    "isWon": false,
    "commission": 0,
    "dealProfit": 0,
    "dealValue": 18854.08,
    "profitMargin": 0.62,
    "closeDate": "2025-09-06",
    "category": "Support"
  },
  {
    "id": "SALE-118",
    "repName": "Olivia Bennett",
    "dealSize": 643.72,
    "isWon": true,
    "commission": 5098.91,
    "dealProfit": 36666.29,
    "dealValue": 57291.08,
    "profitMargin": 0.64,
    "closeDate": "2025-09-10",
    "category": "Training"
  },
  {
    "id": "SALE-119",
    "repName": "Liu Wei",
    "dealSize": 2078.57,
    "isWon": true,
    "commission": 1425.9,
    "dealProfit": 6838.5,
    "dealValue": 14549.99,
    "profitMargin": 0.47,
    "closeDate": "2025-10-13",
    "category": "Services"
  },
  {
    "id": "SALE-120",
    "repName": "Thomas Müller",
    "dealSize": 114.37,
    "isWon": true,
    "commission": 138.39,
    "dealProfit": 720.53,
    "dealValue": 1143.7,
    "profitMargin": 0.63,
    "closeDate": "2025-09-29",
    "category": "Software"
  },
  {
    "id": "SALE-121",
    "repName": "Andreas Schmitt",
    "dealSize": 326.64,
    "isWon": true,
    "commission": 3658.37,
    "dealProfit": 25804.56,
    "dealValue": 32664,
    "profitMargin": 0.79,
    "closeDate": "2025-08-26",
    "category": "Support"
  },
  {
    "id": "SALE-122",
    "repName": "Kim Seung-Min",
    "dealSize": 135.7,
    "isWon": true,
    "commission": 1775.09,
    "dealProfit": 11719.05,
    "dealValue": 17233.9,
    "profitMargin": 0.68,
    "closeDate": "2025-08-20",
    "category": "Support"
  },
  {
    "id": "SALE-123",
    "repName": "Sarah Martinez",
    "dealSize": 543.54,
    "isWon": true,
    "commission": 8750.99,
    "dealProfit": 45657.36,
    "dealValue": 95119.5,
    "profitMargin": 0.48,
    "closeDate": "2025-09-01",
    "category": "Training"
  },
  {
    "id": "SALE-124",
    "repName": "Michael Johnson",
    "dealSize": 366.12,
    "isWon": true,
    "commission": 421.04,
    "dealProfit": 2379.78,
    "dealValue": 3661.2,
    "profitMargin": 0.65,
    "closeDate": "2025-10-01",
    "category": "Support"
  },
  {
    "id": "SALE-125",
    "repName": "Andreas Schmitt",
    "dealSize": 131.98,
    "isWon": true,
    "commission": 872.12,
    "dealProfit": 4749.96,
    "dealValue": 7786.82,
    "profitMargin": 0.61,
    "closeDate": "2025-09-17",
    "category": "Software"
  },
  {
    "id": "SALE-126",
    "repName": "Mei Chen",
    "dealSize": 131.2,
    "isWon": false,
    "commission": 0,
    "dealProfit": 0,
    "dealValue": 9840,
    "profitMargin": 0.64,
    "closeDate": "2025-09-30",
    "category": "Hardware"
  },
  {
    "id": "SALE-127",
    "repName": "Liu Wei",
    "dealSize": 115.22,
    "isWon": true,
    "commission": 489.45,
    "dealProfit": 3193.9,
    "dealValue": 4147.92,
    "profitMargin": 0.77,
    "closeDate": "2025-10-13",
    "category": "Consulting"
  },
  {
    "id": "SALE-128",
    "repName": "James Wilson",
    "dealSize": 637.18,
    "isWon": true,
    "commission": 5897.74,
    "dealProfit": 26086.15,
    "dealValue": 56709.02,
    "profitMargin": 0.46,
    "closeDate": "2025-08-28",
    "category": "Services"
  },
  {
    "id": "SALE-129",
    "repName": "Akira Tanaka",
    "dealSize": 559.31,
    "isWon": true,
    "commission": 6535.54,
    "dealProfit": 33709.61,
    "dealValue": 68795.13,
    "profitMargin": 0.49,
    "closeDate": "2025-07-25",
    "category": "Training"
  },
  {
    "id": "SALE-130",
    "repName": "David Thompson",
    "dealSize": 26943.97,
    "isWon": true,
    "commission": 7194.04,
    "dealProfit": 34757.72,
    "dealValue": 80831.91,
    "profitMargin": 0.43,
    "closeDate": "2025-09-06",
    "category": "Services"
  },
  {
    "id": "SALE-131",
    "repName": "Emma Fischer",
    "dealSize": 408.08,
    "isWon": true,
    "commission": 6977.35,
    "dealProfit": 50805.96,
    "dealValue": 67741.28,
    "profitMargin": 0.75,
    "closeDate": "2025-09-14",
    "category": "Training"
  },
  {
    "id": "SALE-132",
    "repName": "Sarah Martinez",
    "dealSize": 3190.73,
    "isWon": true,
    "commission": 880.64,
    "dealProfit": 3828.88,
    "dealValue": 9572.19,
    "profitMargin": 0.4,
    "closeDate": "2025-08-27",
    "category": "Consulting"
  },
  {
    "id": "SALE-133",
    "repName": "Olivia Bennett",
    "dealSize": 2927.57,
    "isWon": true,
    "commission": 4429.41,
    "dealProfit": 15428.29,
    "dealValue": 49768.69,
    "profitMargin": 0.31,
    "closeDate": "2025-10-02",
    "category": "Services"
  },
  {
    "id": "SALE-134",
    "repName": "Thomas Müller",
    "dealSize": 360.04,
    "isWon": true,
    "commission": 4748.57,
    "dealProfit": 28648.38,
    "dealValue": 39244.36,
    "profitMargin": 0.73,
    "closeDate": "2025-10-10",
    "category": "Support"
  },
  {
    "id": "SALE-135",
    "repName": "David Thompson",
    "dealSize": 3557.37,
    "isWon": false,
    "commission": 0,
    "dealProfit": 0,
    "dealValue": 42688.44,
    "profitMargin": 0.38,
    "closeDate": "2025-09-09",
    "category": "Software"
  },
  {
    "id": "SALE-136",
    "repName": "Sophie Dubois",
    "dealSize": 15849.35,
    "isWon": true,
    "commission": 3011.38,
    "dealProfit": 7607.69,
    "dealValue": 31698.7,
    "profitMargin": 0.24,
    "closeDate": "2025-07-30",
    "category": "Training"
  },
  {
    "id": "SALE-137",
    "repName": "David Thompson",
    "dealSize": 650.38,
    "isWon": true,
    "commission": 2257.47,
    "dealProfit": 12936.06,
    "dealValue": 25364.82,
    "profitMargin": 0.51,
    "closeDate": "2025-10-05",
    "category": "Training"
  },
  {
    "id": "SALE-138",
    "repName": "Akira Tanaka",
    "dealSize": 1661.84,
    "isWon": true,
    "commission": 1911.12,
    "dealProfit": 11466.7,
    "dealValue": 16618.4,
    "profitMargin": 0.69,
    "closeDate": "2025-10-09",
    "category": "Software"
  },
  {
    "id": "SALE-139",
    "repName": "Robert Garcia",
    "dealSize": 391.92,
    "isWon": false,
    "commission": 0,
    "dealProfit": 0,
    "dealValue": 22339.44,
    "profitMargin": 0.67,
    "closeDate": "2025-08-17",
    "category": "Training"
  },
  {
    "id": "SALE-140",
    "repName": "David Thompson",
    "dealSize": 549.58,
    "isWon": false,
    "commission": 0,
    "dealProfit": 0,
    "dealValue": 98374.82,
    "profitMargin": 0.54,
    "closeDate": "2025-09-23",
    "category": "Services"
  },
  {
    "id": "SALE-141",
    "repName": "Andreas Schmitt",
    "dealSize": 354.12,
    "isWon": false,
    "commission": 0,
    "dealProfit": 0,
    "dealValue": 60908.64,
    "profitMargin": 0.76,
    "closeDate": "2025-08-09",
    "category": "Training"
  },
  {
    "id": "SALE-142",
    "repName": "Isabella Fernandez",
    "dealSize": 1608.4,
    "isWon": false,
    "commission": 0,
    "dealProfit": 0,
    "dealValue": 6433.6,
    "profitMargin": 0.69,
    "closeDate": "2025-07-23",
    "category": "Services"
  },
  {
    "id": "SALE-143",
    "repName": "Ravi Patel",
    "dealSize": 125.25,
    "isWon": true,
    "commission": 2511.01,
    "dealProfit": 15021.23,
    "dealValue": 22419.75,
    "profitMargin": 0.67,
    "closeDate": "2025-08-07",
    "category": "Software"
  },
  {
    "id": "SALE-144",
    "repName": "Michael Johnson",
    "dealSize": 374.21,
    "isWon": true,
    "commission": 2495.98,
    "dealProfit": 15192.93,
    "dealValue": 21704.18,
    "profitMargin": 0.7,
    "closeDate": "2025-09-20",
    "category": "Consulting"
  },
  {
    "id": "SALE-145",
    "repName": "Emily Davis",
    "dealSize": 26126.28,
    "isWon": false,
    "commission": 0,
    "dealProfit": 0,
    "dealValue": 78378.84,
    "profitMargin": 0.43,
    "closeDate": "2025-09-15",
    "category": "Consulting"
  },
  {
    "id": "SALE-146",
    "repName": "Michael Johnson",
    "dealSize": 1497.07,
    "isWon": true,
    "commission": 344.33,
    "dealProfit": 2395.31,
    "dealValue": 2994.14,
    "profitMargin": 0.8,
    "closeDate": "2025-08-10",
    "category": "Services"
  },
  {
    "id": "SALE-147",
    "repName": "Andreas Schmitt",
    "dealSize": 25108.76,
    "isWon": false,
    "commission": 0,
    "dealProfit": 0,
    "dealValue": 50217.52,
    "profitMargin": 0.38,
    "closeDate": "2025-08-22",
    "category": "Services"
  },
  {
    "id": "SALE-148",
    "repName": "Akira Tanaka",
    "dealSize": 25409.32,
    "isWon": true,
    "commission": 2413.89,
    "dealProfit": 11434.19,
    "dealValue": 25409.32,
    "profitMargin": 0.45,
    "closeDate": "2025-07-22",
    "category": "Hardware"
  },
  {
    "id": "SALE-149",
    "repName": "Liu Wei",
    "dealSize": 2535.99,
    "isWon": false,
    "commission": 0,
    "dealProfit": 0,
    "dealValue": 5071.98,
    "profitMargin": 0.54,
    "closeDate": "2025-09-01",
    "category": "Hardware"
  },
  {
    "id": "SALE-150",
    "repName": "David Thompson",
    "dealSize": 112.2,
    "isWon": false,
    "commission": 0,
    "dealProfit": 0,
    "dealValue": 20981.4,
    "profitMargin": 0.74,
    "closeDate": "2025-08-07",
    "category": "Training"
  },
  {
    "id": "SALE-151",
    "repName": "Emma Fischer",
    "dealSize": 3094.02,
    "isWon": true,
    "commission": 4879.27,
    "dealProfit": 18223.78,
    "dealValue": 58786.38,
    "profitMargin": 0.31,
    "closeDate": "2025-09-28",
    "category": "Training"
  },
  {
    "id": "SALE-152",
    "repName": "Sarah Martinez",
    "dealSize": 2164.44,
    "isWon": true,
    "commission": 3783.44,
    "dealProfit": 20150.94,
    "dealValue": 41124.36,
    "profitMargin": 0.49,
    "closeDate": "2025-08-25",
    "category": "Software"
  },
  {
    "id": "SALE-153",
    "repName": "Akira Tanaka",
    "dealSize": 2161.93,
    "isWon": false,
    "commission": 0,
    "dealProfit": 0,
    "dealValue": 36752.81,
    "profitMargin": 0.62,
    "closeDate": "2025-09-01",
    "category": "Hardware"
  },
  {
    "id": "SALE-154",
    "repName": "Thomas Müller",
    "dealSize": 17156.43,
    "isWon": true,
    "commission": 1732.8,
    "dealProfit": 4117.54,
    "dealValue": 17156.43,
    "profitMargin": 0.24,
    "closeDate": "2025-08-07",
    "category": "Software"
  },
  {
    "id": "SALE-155",
    "repName": "Liu Wei",
    "dealSize": 2529.9,
    "isWon": false,
    "commission": 0,
    "dealProfit": 0,
    "dealValue": 37948.5,
    "profitMargin": 0.64,
    "closeDate": "2025-08-12",
    "category": "Training"
  },
  {
    "id": "SALE-156",
    "repName": "Emily Davis",
    "dealSize": 136.37,
    "isWon": false,
    "commission": 0,
    "dealProfit": 0,
    "dealValue": 15137.07,
    "profitMargin": 0.67,
    "closeDate": "2025-10-03",
    "category": "Services"
  },
  {
    "id": "SALE-157",
    "repName": "Emily Davis",
    "dealSize": 620.15,
    "isWon": true,
    "commission": 7171.41,
    "dealProfit": 41711.29,
    "dealValue": 73177.7,
    "profitMargin": 0.57,
    "closeDate": "2025-07-29",
    "category": "Support"
  },
  {
    "id": "SALE-158",
    "repName": "James Wilson",
    "dealSize": 1727.74,
    "isWon": false,
    "commission": 0,
    "dealProfit": 0,
    "dealValue": 6910.96,
    "profitMargin": 0.64,
    "closeDate": "2025-08-18",
    "category": "Software"
  },
  {
    "id": "SALE-159",
    "repName": "Andreas Schmitt",
    "dealSize": 120.51,
    "isWon": true,
    "commission": 1133.76,
    "dealProfit": 6478.62,
    "dealValue": 10122.84,
    "profitMargin": 0.64,
    "closeDate": "2025-09-01",
    "category": "Software"
  },
  {
    "id": "SALE-160",
    "repName": "Andreas Schmitt",
    "dealSize": 321.36,
    "isWon": true,
    "commission": 4427.06,
    "dealProfit": 27669.1,
    "dealValue": 39527.28,
    "profitMargin": 0.7,
    "closeDate": "2025-07-25",
    "category": "Services"
  },
  {
    "id": "SALE-161",
    "repName": "James Wilson",
    "dealSize": 8645.54,
    "isWon": true,
    "commission": 8092.23,
    "dealProfit": 14005.77,
    "dealValue": 77809.86,
    "profitMargin": 0.18,
    "closeDate": "2025-08-10",
    "category": "Support"
  },
  {
    "id": "SALE-162",
    "repName": "Olivia Bennett",
    "dealSize": 116.19,
    "isWon": false,
    "commission": 0,
    "dealProfit": 0,
    "dealValue": 19403.73,
    "profitMargin": 0.73,
    "closeDate": "2025-07-25",
    "category": "Support"
  },
  {
    "id": "SALE-163",
    "repName": "Sophie Dubois",
    "dealSize": 19172.56,
    "isWon": false,
    "commission": 0,
    "dealProfit": 0,
    "dealValue": 38345.12,
    "profitMargin": 0.28,
    "closeDate": "2025-08-23",
    "category": "Consulting"
  },
  {
    "id": "SALE-164",
    "repName": "James Wilson",
    "dealSize": 693.84,
    "isWon": true,
    "commission": 2236.94,
    "dealProfit": 10754.52,
    "dealValue": 21509.04,
    "profitMargin": 0.5,
    "closeDate": "2025-10-05",
    "category": "Software"
  },
  {
    "id": "SALE-165",
    "repName": "James Wilson",
    "dealSize": 1377.44,
    "isWon": true,
    "commission": 2903.64,
    "dealProfit": 17796.52,
    "dealValue": 23416.48,
    "profitMargin": 0.76,
    "closeDate": "2025-08-10",
    "category": "Training"
  },
  {
    "id": "SALE-166",
    "repName": "James Wilson",
    "dealSize": 9897.85,
    "isWon": true,
    "commission": 11323.14,
    "dealProfit": 20686.51,
    "dealValue": 108876.35,
    "profitMargin": 0.19,
    "closeDate": "2025-09-12",
    "category": "Software"
  },
  {
    "id": "SALE-167",
    "repName": "Emily Davis",
    "dealSize": 2012.45,
    "isWon": true,
    "commission": 3549.96,
    "dealProfit": 22458.94,
    "dealValue": 36224.1,
    "profitMargin": 0.62,
    "closeDate": "2025-09-05",
    "category": "Hardware"
  },
  {
    "id": "SALE-168",
    "repName": "Emma Fischer",
    "dealSize": 341.13,
    "isWon": true,
    "commission": 4146.09,
    "dealProfit": 27774.8,
    "dealValue": 40253.34,
    "profitMargin": 0.69,
    "closeDate": "2025-08-26",
    "category": "Support"
  },
  {
    "id": "SALE-169",
    "repName": "Carlos Rodriguez",
    "dealSize": 19750.62,
    "isWon": true,
    "commission": 3752.62,
    "dealProfit": 8690.27,
    "dealValue": 39501.24,
    "profitMargin": 0.22,
    "closeDate": "2025-09-17",
    "category": "Consulting"
  },
  {
    "id": "SALE-170",
    "repName": "Jessica Lee",
    "dealSize": 326.98,
    "isWon": false,
    "commission": 0,
    "dealProfit": 0,
    "dealValue": 31390.08,
    "profitMargin": 0.71,
    "closeDate": "2025-08-31",
    "category": "Software"
  },
  {
    "id": "SALE-171",
    "repName": "Michael Johnson",
    "dealSize": 8571.77,
    "isWon": true,
    "commission": 13843.41,
    "dealProfit": 27686.82,
    "dealValue": 145720.09,
    "profitMargin": 0.19,
    "closeDate": "2025-08-16",
    "category": "Support"
  },
  {
    "id": "SALE-172",
    "repName": "Mei Chen",
    "dealSize": 27124.39,
    "isWon": false,
    "commission": 0,
    "dealProfit": 0,
    "dealValue": 27124.39,
    "profitMargin": 0.36,
    "closeDate": "2025-07-19",
    "category": "Software"
  },
  {
    "id": "SALE-173",
    "repName": "James Wilson",
    "dealSize": 8408.88,
    "isWon": true,
    "commission": 2623.57,
    "dealProfit": 7820.26,
    "dealValue": 25226.64,
    "profitMargin": 0.31,
    "closeDate": "2025-07-31",
    "category": "Consulting"
  },
  {
    "id": "SALE-174",
    "repName": "Liu Wei",
    "dealSize": 8877.84,
    "isWon": false,
    "commission": 0,
    "dealProfit": 0,
    "dealValue": 79900.56,
    "profitMargin": 0.32,
    "closeDate": "2025-08-09",
    "category": "Services"
  },
  {
    "id": "SALE-175",
    "repName": "Michael Johnson",
    "dealSize": 311.53,
    "isWon": true,
    "commission": 2830.25,
    "dealProfit": 18704.26,
    "dealValue": 24610.87,
    "profitMargin": 0.76,
    "closeDate": "2025-09-19",
    "category": "Support"
  },
  {
    "id": "SALE-176",
    "repName": "David Thompson",
    "dealSize": 530.81,
    "isWon": true,
    "commission": 141.73,
    "dealProfit": 812.14,
    "dealValue": 1592.43,
    "profitMargin": 0.51,
    "closeDate": "2025-07-29",
    "category": "Software"
  },
  {
    "id": "SALE-177",
    "repName": "Emma Fischer",
    "dealSize": 369.46,
    "isWon": false,
    "commission": 0,
    "dealProfit": 0,
    "dealValue": 27340.04,
    "profitMargin": 0.72,
    "closeDate": "2025-08-16",
    "category": "Consulting"
  },
  {
    "id": "SALE-178",
    "repName": "Carlos Rodriguez",
    "dealSize": 131.94,
    "isWon": false,
    "commission": 0,
    "dealProfit": 0,
    "dealValue": 2638.8,
    "profitMargin": 0.63,
    "closeDate": "2025-07-19",
    "category": "Software"
  },
  {
    "id": "SALE-179",
    "repName": "Liu Wei",
    "dealSize": 364.49,
    "isWon": false,
    "commission": 0,
    "dealProfit": 0,
    "dealValue": 57589.42,
    "profitMargin": 0.77,
    "closeDate": "2025-09-02",
    "category": "Training"
  },
  {
    "id": "SALE-180",
    "repName": "Valentina Diaz",
    "dealSize": 2599.52,
    "isWon": true,
    "commission": 4315.2,
    "dealProfit": 25995.2,
    "dealValue": 51990.4,
    "profitMargin": 0.5,
    "closeDate": "2025-08-03",
    "category": "Consulting"
  },
  {
    "id": "SALE-181",
    "repName": "Isabella Fernandez",
    "dealSize": 318.48,
    "isWon": true,
    "commission": 1527.43,
    "dealProfit": 10930.23,
    "dealValue": 14013.12,
    "profitMargin": 0.78,
    "closeDate": "2025-08-31",
    "category": "Training"
  },
  {
    "id": "SALE-182",
    "repName": "Andreas Schmitt",
    "dealSize": 8524.47,
    "isWon": true,
    "commission": 11763.77,
    "dealProfit": 26852.08,
    "dealValue": 127867.05,
    "profitMargin": 0.21,
    "closeDate": "2025-08-29",
    "category": "Support"
  },
  {
    "id": "SALE-183",
    "repName": "Carlos Rodriguez",
    "dealSize": 30064.5,
    "isWon": false,
    "commission": 0,
    "dealProfit": 0,
    "dealValue": 60129,
    "profitMargin": 0.43,
    "closeDate": "2025-08-02",
    "category": "Consulting"
  },
  {
    "id": "SALE-184",
    "repName": "Liu Wei",
    "dealSize": 127.31,
    "isWon": false,
    "commission": 0,
    "dealProfit": 0,
    "dealValue": 17823.4,
    "profitMargin": 0.75,
    "closeDate": "2025-08-04",
    "category": "Consulting"
  },
  {
    "id": "SALE-185",
    "repName": "Ravi Patel",
    "dealSize": 14826.92,
    "isWon": true,
    "commission": 2728.15,
    "dealProfit": 8599.61,
    "dealValue": 29653.84,
    "profitMargin": 0.29,
    "closeDate": "2025-09-15",
    "category": "Software"
  },
  {
    "id": "SALE-186",
    "repName": "Emily Davis",
    "dealSize": 10052.42,
    "isWon": true,
    "commission": 985.14,
    "dealProfit": 4925.69,
    "dealValue": 10052.42,
    "profitMargin": 0.49,
    "closeDate": "2025-08-09",
    "category": "Consulting"
  },
  {
    "id": "SALE-187",
    "repName": "Michael Johnson",
    "dealSize": 518.99,
    "isWon": true,
    "commission": 4585.28,
    "dealProfit": 25098.36,
    "dealValue": 48266.07,
    "profitMargin": 0.52,
    "closeDate": "2025-10-02",
    "category": "Training"
  },
  {
    "id": "SALE-188",
    "repName": "Mateo Lopez",
    "dealSize": 392.68,
    "isWon": true,
    "commission": 2247.7,
    "dealProfit": 16751.73,
    "dealValue": 21204.72,
    "profitMargin": 0.79,
    "closeDate": "2025-09-29",
    "category": "Services"
  },
  {
    "id": "SALE-189",
    "repName": "Mateo Lopez",
    "dealSize": 26924,
    "isWon": true,
    "commission": 2315.46,
    "dealProfit": 9692.64,
    "dealValue": 26924,
    "profitMargin": 0.36,
    "closeDate": "2025-09-30",
    "category": "Training"
  },
  {
    "id": "SALE-190",
    "repName": "Andreas Schmitt",
    "dealSize": 639.9,
    "isWon": true,
    "commission": 10949.97,
    "dealProfit": 71412.84,
    "dealValue": 119021.4,
    "profitMargin": 0.6,
    "closeDate": "2025-09-30",
    "category": "Support"
  },
  {
    "id": "SALE-191",
    "repName": "David Thompson",
    "dealSize": 3196.25,
    "isWon": true,
    "commission": 1137.87,
    "dealProfit": 4730.45,
    "dealValue": 12785,
    "profitMargin": 0.37,
    "closeDate": "2025-10-08",
    "category": "Consulting"
  },
  {
    "id": "SALE-192",
    "repName": "Emily Davis",
    "dealSize": 599.6,
    "isWon": false,
    "commission": 0,
    "dealProfit": 0,
    "dealValue": 7195.2,
    "profitMargin": 0.45,
    "closeDate": "2025-10-05",
    "category": "Hardware"
  },
  {
    "id": "SALE-193",
    "repName": "Carlos Rodriguez",
    "dealSize": 17614.39,
    "isWon": true,
    "commission": 1673.37,
    "dealProfit": 5284.32,
    "dealValue": 17614.39,
    "profitMargin": 0.3,
    "closeDate": "2025-09-03",
    "category": "Software"
  },
  {
    "id": "SALE-194",
    "repName": "Emily Davis",
    "dealSize": 5835.72,
    "isWon": true,
    "commission": 571.9,
    "dealProfit": 1867.43,
    "dealValue": 5835.72,
    "profitMargin": 0.32,
    "closeDate": "2025-09-03",
    "category": "Support"
  },
  {
    "id": "SALE-195",
    "repName": "Liu Wei",
    "dealSize": 516.91,
    "isWon": true,
    "commission": 9219.61,
    "dealProfit": 47979.59,
    "dealValue": 94077.62,
    "profitMargin": 0.51,
    "closeDate": "2025-08-09",
    "category": "Software"
  },
  {
    "id": "SALE-196",
    "repName": "Carlos Rodriguez",
    "dealSize": 104.08,
    "isWon": false,
    "commission": 0,
    "dealProfit": 0,
    "dealValue": 6452.96,
    "profitMargin": 0.7,
    "closeDate": "2025-08-18",
    "category": "Support"
  },
  {
    "id": "SALE-197",
    "repName": "Akira Tanaka",
    "dealSize": 25918.54,
    "isWon": false,
    "commission": 0,
    "dealProfit": 0,
    "dealValue": 51837.08,
    "profitMargin": 0.36,
    "closeDate": "2025-10-04",
    "category": "Training"
  },
  {
    "id": "SALE-198",
    "repName": "Ravi Patel",
    "dealSize": 627.48,
    "isWon": false,
    "commission": 0,
    "dealProfit": 0,
    "dealValue": 32001.48,
    "profitMargin": 0.45,
    "closeDate": "2025-07-20",
    "category": "Services"
  },
  {
    "id": "SALE-199",
    "repName": "Thomas Müller",
    "dealSize": 14880.71,
    "isWon": true,
    "commission": 1502.95,
    "dealProfit": 4761.83,
    "dealValue": 14880.71,
    "profitMargin": 0.32,
    "closeDate": "2025-07-23",
    "category": "Support"
  },
  {
    "id": "SALE-200",
    "repName": "Michael Johnson",
    "dealSize": 19996.3,
    "isWon": false,
    "commission": 0,
    "dealProfit": 0,
    "dealValue": 59988.9,
    "profitMargin": 0.28,
    "closeDate": "2025-08-13",
    "category": "Hardware"
  },
  {
    "id": "SALE-201",
    "repName": "Carlos Rodriguez",
    "dealSize": 8587.28,
    "isWon": true,
    "commission": 10605.29,
    "dealProfit": 23443.27,
    "dealValue": 111634.64,
    "profitMargin": 0.21,
    "closeDate": "2025-09-04",
    "category": "Services"
  },
  {
    "id": "SALE-202",
    "repName": "Andreas Schmitt",
    "dealSize": 1968.82,
    "isWon": true,
    "commission": 2716.97,
    "dealProfit": 13289.54,
    "dealValue": 29532.3,
    "profitMargin": 0.45,
    "closeDate": "2025-08-23",
    "category": "Software"
  },
  {
    "id": "SALE-203",
    "repName": "Thomas Müller",
    "dealSize": 129.94,
    "isWon": true,
    "commission": 2122.57,
    "dealProfit": 13156.43,
    "dealValue": 17541.9,
    "profitMargin": 0.75,
    "closeDate": "2025-08-10",
    "category": "Consulting"
  },
  {
    "id": "SALE-204",
    "repName": "Akira Tanaka",
    "dealSize": 8110.21,
    "isWon": true,
    "commission": 1540.94,
    "dealProfit": 6488.17,
    "dealValue": 16220.42,
    "profitMargin": 0.4,
    "closeDate": "2025-08-31",
    "category": "Services"
  },
  {
    "id": "SALE-205",
    "repName": "Isabella Fernandez",
    "dealSize": 17056.11,
    "isWon": true,
    "commission": 3035.99,
    "dealProfit": 6822.44,
    "dealValue": 34112.22,
    "profitMargin": 0.2,
    "closeDate": "2025-08-31",
    "category": "Hardware"
  },
  {
    "id": "SALE-206",
    "repName": "Olivia Bennett",
    "dealSize": 1754.71,
    "isWon": true,
    "commission": 1147.58,
    "dealProfit": 8317.33,
    "dealValue": 10528.26,
    "profitMargin": 0.79,
    "closeDate": "2025-09-09",
    "category": "Hardware"
  },
  {
    "id": "SALE-207",
    "repName": "Thomas Müller",
    "dealSize": 31991.23,
    "isWon": false,
    "commission": 0,
    "dealProfit": 0,
    "dealValue": 31991.23,
    "profitMargin": 0.33,
    "closeDate": "2025-07-29",
    "category": "Support"
  },
  {
    "id": "SALE-208",
    "repName": "Andreas Schmitt",
    "dealSize": 1662.47,
    "isWon": false,
    "commission": 0,
    "dealProfit": 0,
    "dealValue": 24937.05,
    "profitMargin": 0.7,
    "closeDate": "2025-09-28",
    "category": "Services"
  },
  {
    "id": "SALE-209",
    "repName": "Andreas Schmitt",
    "dealSize": 619.61,
    "isWon": false,
    "commission": 0,
    "dealProfit": 0,
    "dealValue": 81168.91,
    "profitMargin": 0.58,
    "closeDate": "2025-08-04",
    "category": "Training"
  },
  {
    "id": "SALE-210",
    "repName": "Valentina Diaz",
    "dealSize": 3500.65,
    "isWon": false,
    "commission": 0,
    "dealProfit": 0,
    "dealValue": 14002.6,
    "profitMargin": 0.38,
    "closeDate": "2025-09-19",
    "category": "Training"
  },
  {
    "id": "SALE-211",
    "repName": "Andreas Schmitt",
    "dealSize": 329.47,
    "isWon": true,
    "commission": 2398.54,
    "dealProfit": 15419.2,
    "dealValue": 21415.55,
    "profitMargin": 0.72,
    "closeDate": "2025-08-28",
    "category": "Consulting"
  },
  {
    "id": "SALE-212",
    "repName": "Carlos Rodriguez",
    "dealSize": 670.32,
    "isWon": true,
    "commission": 5285.47,
    "dealProfit": 35051.03,
    "dealValue": 55636.56,
    "profitMargin": 0.63,
    "closeDate": "2025-07-31",
    "category": "Services"
  },
  {
    "id": "SALE-213",
    "repName": "Isabella Fernandez",
    "dealSize": 336.34,
    "isWon": true,
    "commission": 3592.78,
    "dealProfit": 22413.7,
    "dealValue": 32961.32,
    "profitMargin": 0.68,
    "closeDate": "2025-09-21",
    "category": "Services"
  },
  {
    "id": "SALE-214",
    "repName": "James Wilson",
    "dealSize": 522.65,
    "isWon": true,
    "commission": 8588.18,
    "dealProfit": 50373.01,
    "dealValue": 82578.7,
    "profitMargin": 0.61,
    "closeDate": "2025-09-13",
    "category": "Training"
  },
  {
    "id": "SALE-215",
    "repName": "James Wilson",
    "dealSize": 8438.44,
    "isWon": true,
    "commission": 2632.79,
    "dealProfit": 8100.9,
    "dealValue": 25315.32,
    "profitMargin": 0.32,
    "closeDate": "2025-08-20",
    "category": "Services"
  },
  {
    "id": "SALE-216",
    "repName": "Thomas Müller",
    "dealSize": 350.32,
    "isWon": false,
    "commission": 0,
    "dealProfit": 0,
    "dealValue": 19968.24,
    "profitMargin": 0.76,
    "closeDate": "2025-08-24",
    "category": "Consulting"
  },
  {
    "id": "SALE-217",
    "repName": "Liu Wei",
    "dealSize": 375.3,
    "isWon": false,
    "commission": 0,
    "dealProfit": 0,
    "dealValue": 6004.8,
    "profitMargin": 0.7,
    "closeDate": "2025-07-21",
    "category": "Consulting"
  },
  {
    "id": "SALE-218",
    "repName": "Thomas Müller",
    "dealSize": 2674.77,
    "isWon": true,
    "commission": 3511.97,
    "dealProfit": 12170.2,
    "dealValue": 34772.01,
    "profitMargin": 0.35,
    "closeDate": "2025-08-27",
    "category": "Software"
  },
  {
    "id": "SALE-219",
    "repName": "Thomas Müller",
    "dealSize": 128.12,
    "isWon": false,
    "commission": 0,
    "dealProfit": 0,
    "dealValue": 13836.96,
    "profitMargin": 0.75,
    "closeDate": "2025-08-24",
    "category": "Software"
  },
  {
    "id": "SALE-220",
    "repName": "Sarah Martinez",
    "dealSize": 20144.21,
    "isWon": true,
    "commission": 5559.8,
    "dealProfit": 15108.16,
    "dealValue": 60432.63,
    "profitMargin": 0.25,
    "closeDate": "2025-07-31",
    "category": "Support"
  },
  {
    "id": "SALE-221",
    "repName": "Mateo Lopez",
    "dealSize": 15043.33,
    "isWon": true,
    "commission": 3881.18,
    "dealProfit": 10379.9,
    "dealValue": 45129.99,
    "profitMargin": 0.23,
    "closeDate": "2025-08-15",
    "category": "Services"
  },
  {
    "id": "SALE-222",
    "repName": "Liu Wei",
    "dealSize": 5623.09,
    "isWon": true,
    "commission": 5510.63,
    "dealProfit": 22492.36,
    "dealValue": 56230.9,
    "profitMargin": 0.4,
    "closeDate": "2025-09-21",
    "category": "Services"
  },
  {
    "id": "SALE-223",
    "repName": "Emily Davis",
    "dealSize": 5634.18,
    "isWon": false,
    "commission": 0,
    "dealProfit": 0,
    "dealValue": 61975.98,
    "profitMargin": 0.49,
    "closeDate": "2025-08-16",
    "category": "Support"
  },
  {
    "id": "SALE-224",
    "repName": "Mateo Lopez",
    "dealSize": 100.34,
    "isWon": true,
    "commission": 989.15,
    "dealProfit": 6345.5,
    "dealValue": 9331.62,
    "profitMargin": 0.68,
    "closeDate": "2025-08-01",
    "category": "Services"
  },
  {
    "id": "SALE-225",
    "repName": "Liu Wei",
    "dealSize": 414.8,
    "isWon": true,
    "commission": 8320.89,
    "dealProfit": 43014.76,
    "dealValue": 70516,
    "profitMargin": 0.61,
    "closeDate": "2025-08-09",
    "category": "Consulting"
  },
  {
    "id": "SALE-226",
    "repName": "Carlos Rodriguez",
    "dealSize": 109.59,
    "isWon": true,
    "commission": 894.8,
    "dealProfit": 5757.86,
    "dealValue": 7780.89,
    "profitMargin": 0.74,
    "closeDate": "2025-08-23",
    "category": "Services"
  },
  {
    "id": "SALE-227",
    "repName": "Liu Wei",
    "dealSize": 10226.4,
    "isWon": false,
    "commission": 0,
    "dealProfit": 0,
    "dealValue": 204528,
    "profitMargin": 0.29,
    "closeDate": "2025-08-29",
    "category": "Support"
  },
  {
    "id": "SALE-228",
    "repName": "Liu Wei",
    "dealSize": 523.58,
    "isWon": true,
    "commission": 359.18,
    "dealProfit": 2199.04,
    "dealValue": 3665.06,
    "profitMargin": 0.6,
    "closeDate": "2025-09-13",
    "category": "Training"
  },
  {
    "id": "SALE-229",
    "repName": "Andreas Schmitt",
    "dealSize": 8548.95,
    "isWon": true,
    "commission": 15730.07,
    "dealProfit": 47874.12,
    "dealValue": 170979,
    "profitMargin": 0.28,
    "closeDate": "2025-10-13",
    "category": "Training"
  },
  {
    "id": "SALE-230",
    "repName": "Michael Johnson",
    "dealSize": 8541.75,
    "isWon": false,
    "commission": 0,
    "dealProfit": 0,
    "dealValue": 85417.5,
    "profitMargin": 0.24,
    "closeDate": "2025-10-04",
    "category": "Support"
  },
  {
    "id": "SALE-231",
    "repName": "Sophie Dubois",
    "dealSize": 28246.01,
    "isWon": true,
    "commission": 5366.74,
    "dealProfit": 20902.05,
    "dealValue": 56492.02,
    "profitMargin": 0.37,
    "closeDate": "2025-08-14",
    "category": "Hardware"
  },
  {
    "id": "SALE-232",
    "repName": "Olivia Bennett",
    "dealSize": 379.46,
    "isWon": false,
    "commission": 0,
    "dealProfit": 0,
    "dealValue": 62231.44,
    "profitMargin": 0.76,
    "closeDate": "2025-07-24",
    "category": "Software"
  },
  {
    "id": "SALE-233",
    "repName": "Ravi Patel",
    "dealSize": 19586.07,
    "isWon": true,
    "commission": 3603.84,
    "dealProfit": 10184.76,
    "dealValue": 39172.14,
    "profitMargin": 0.26,
    "closeDate": "2025-08-30",
    "category": "Hardware"
  }
]
